MANIFEST.in
README.md
setup.cfg
setup.py
apple_music_analyser/DataVisualization.py
apple_music_analyser/Parser.py
apple_music_analyser/Process.py
apple_music_analyser/Query.py
apple_music_analyser/Track.py
apple_music_analyser/Utility.py
apple_music_analyser/VisualizationDataframe.py
apple_music_analyser/__init__.py
apple_music_analyser/setup.py
apple_music_analyser.egg-info/PKG-INFO
apple_music_analyser.egg-info/SOURCES.txt
apple_music_analyser.egg-info/dependency_links.txt
apple_music_analyser.egg-info/requires.txt
apple_music_analyser.egg-info/top_level.txt
apple_music_analyser/tests/__init__.py
apple_music_analyser/tests/test_Parser.py
apple_music_analyser/tests/test_Process.py
apple_music_analyser/tests/test_Query.py
apple_music_analyser/tests/test_Track.py
apple_music_analyser/tests/test_Utils.py
apple_music_analyser/tests/test_VisualizationDataframe.py
apple_music_analyser/tests/test_df.zip