Metadata-Version: 2.1
Name: apple-music-analyser
Version: 0.2.0
Summary: Data wrangling and processing for visualization of the usage of the Apple Music service
Home-page: https://github.com/acoullandreau/apple_dashboard
Author: Alexina Coullandreau
License: MIT
Platform: UNKNOWN
Classifier: Development Status :: 4 - Beta
Classifier: License :: OSI Approved :: MIT License
Classifier: Programming Language :: Python :: 3
Classifier: Programming Language :: Python :: 3.7
Classifier: Intended Audience :: Developers
Classifier: Topic :: Scientific/Engineering :: Information Analysis
Classifier: Topic :: Scientific/Engineering :: Visualization
Requires-Python: >=3.6
